reversion-0.1.dist-info/METADATA
reversion-0.1.dist-info/WHEEL
reversion-0.1.dist-info/entry_points.txt
reversion/__init__.py
reversion/__main__.py
reversion/deltas.py
reversion-0.1.dist-info/RECORD
