Metadata-Version: 1.2
Name: reversion
Version: 0.1
Summary: Easily update version numbers across your project.
Home-page: https://github.com/takluyver/reversion
License: UNKNOWN
Author: Thomas Kluyver
Author-email: thomas@kluyver.me.uk
Requires-Python: 3
Classifier: License :: OSI Approved :: MIT License
Classifier: Intended Audience :: Developers
Classifier: Programming Language :: Python :: 3
Classifier: Topic :: Software Development
Requires-Dist: toml
